xneos/__init__.py
xneos/neos.py
xneos/quickstart.py
xneos/templates/xneos_main.py
xneos/templates/xneos_template.xlsm
xneos-0.1.0.dist-info/licenses/LICENSE
xneos-0.1.0.dist-info/METADATA
xneos-0.1.0.dist-info/WHEEL
xneos-0.1.0.dist-info/entry_points.txt
xneos-0.1.0.dist-info/top_level.txt
xneos-0.1.0.dist-info/RECORD
