Metadata-Version: 2.4
Name: xneos
Version: 0.1.0
Summary: A helping tool to submit jobs to NEOS from Excel
Home-page: https://github.com/jerronl/xneos
Author: Jerron
Author-email: jerron@gmail.com
Classifier: Programming Language :: Python :: 3
Classifier: Operating System :: OS Independent
Classifier: License :: OSI Approved :: MIT License
Requires-Python: >=3.7
License-File: LICENSE
Requires-Dist: xlwings
Requires-Dist: numpy
Dynamic: author
Dynamic: author-email
Dynamic: classifier
Dynamic: description
Dynamic: description-content-type
Dynamic: home-page
Dynamic: license-file
Dynamic: requires-dist
Dynamic: requires-python
Dynamic: summary
